toolcall/openai/_common/__init__.py
toolcall/openai/_common/_call.py
toolcall/openai/_common/_definition.py
toolcall/openai/_common/_result.py
toolcall/openai/aio/__init__.py
toolcall/openai/aio/_group.py
toolcall/openai/aio/_tool.py
toolcall/openai/core/__init__.py
toolcall/openai/core/_group.py
toolcall/openai/core/_tool.py
toolcall-2.1.1.dist-info/METADATA
toolcall-2.1.1.dist-info/WHEEL
toolcall-2.1.1.dist-info/licenses/LICENSE
toolcall-2.1.1.dist-info/RECORD
