Metadata-Version: 2.4
Name: toolcall
Version: 2.1.1
Summary: The agentic framework for building without an agentic framework.
Author-email: Ryan Young <dev@ryayoung.com>
License-Expression: MIT
License-File: LICENSE
Classifier: Development Status :: 3 - Alpha
Classifier: Intended Audience :: Developers
Classifier: License :: OSI Approved :: MIT License
Classifier: Operating System :: OS Independent
Classifier: Programming Language :: Python :: 3.12
Classifier: Programming Language :: Python :: 3.13
Classifier: Topic :: Software Development :: Libraries
Requires-Python: >=3.12
Requires-Dist: openai>=1.99.6
Requires-Dist: pydantic>=2.11
